bwtrack/__init__.py
bwtrack/bwtrack.py
bwtrack-1.4.dist-info/METADATA
bwtrack-1.4.dist-info/WHEEL
bwtrack-1.4.dist-info/licenses/LICENSE
bwtrack-1.4.dist-info/RECORD
