Metadata-Version: 2.1
Name: bwtrack
Version: 1.4
Summary: A small particle tracking package that detects black and white particles.
Project-URL: Homepage, https://github.com/zloverty/bwtrack
Project-URL: Bug Tracker, https://github.com/zloverty/bwtrack/issues
Author-email: Zhengyang Liu <liuzy19911112@gmail.com>
License-File: LICENSE
Classifier: License :: OSI Approved :: MIT License
Classifier: Operating System :: OS Independent
Classifier: Programming Language :: Python :: 3
Requires-Python: >=3.9
Requires-Dist: matplotlib
Requires-Dist: myimagelib
Requires-Dist: numpy
Requires-Dist: pandas
Requires-Dist: scikit-image
Requires-Dist: scipy
